{
  "label": "Grade Level",
  "name": "ecm_grade_level",
  "prevent_duplicate": {
    "error_message": "There is an existing grade level:",
    "error_title": "Duplicate Grade Level",
    "condition": "AND",
    "fields": {
		"name":{
			"skip_if_empty": 1
		}
	}
  },
  "fields": {
    "name": "ecm_grade_level94",
    "source": "ecm_grade_level95",
    "comment": "ecm_grade_level96"
  },
  "labels": {
    "ecm_grade_level94": {
      "table_name": "dle32878375463",
      "serial_number": "10",
      "field_type": "undefined",
      "filed_length": "undefined",
      "field_label": "Grade Level",
      "display_field_label": "Grade Level",
      "form_field": "text",
      "form_field_options": "",
      "required_field": "yes",
      "data": [],
      "database_objects": "",
      "attributes": "",
      "class": "",
      "default_appearance_in_table_fields": "show",
      "display_position": "display-in-table-row",
      "acceptable_files_format": "",
      "field_id": "ecm_grade_level94",
      "group": "",
      "id": "dds32878385075",
      "serial_num": "94",
      "created_by": "35991362173",
      "modification_date": "1685695751",
      "creation_date": "1685695751",
      "modified_by": "35991362173",
      "text": "Grade Level",
      "field_key": "ecm_grade_level94",
      "table": "ecm_grade_level",
      "field_identifier": "name"
    },
    "ecm_grade_level95": {
      "table_name": "dle32878375463",
      "serial_number": "20",
      "field_type": "undefined",
      "filed_length": "undefined",
      "field_label": "Source",
      "display_field_label": "",
      "form_field": "text",
      "form_field_options": "",
      "required_field": "no",
      "data": [],
      "database_objects": "",
      "attributes": "",
      "class": "",
      "default_appearance_in_table_fields": "hide",
      "display_position": "display-in-table-row",
      "acceptable_files_format": "",
      "field_id": "ecm_grade_level95",
      "group": "",
      "id": "dds32878389449",
      "serial_num": "95",
      "created_by": "35991362173",
      "modification_date": "1685695795",
      "creation_date": "1685695795",
      "modified_by": "35991362173",
      "text": "Source",
      "field_key": "ecm_grade_level95",
      "table": "ecm_grade_level",
      "field_identifier": "source"
    },
    "ecm_grade_level96": {
      "table_name": "dle32878375463",
      "serial_number": "30",
      "field_type": "undefined",
      "filed_length": "undefined",
      "field_label": "Comment",
      "display_field_label": "",
      "form_field": "textarea",
      "form_field_options": "",
      "required_field": "no",
      "data": [],
      "database_objects": "",
      "attributes": "",
      "class": "",
      "default_appearance_in_table_fields": "show",
      "display_position": "display-in-table-row",
      "acceptable_files_format": "",
      "field_id": "ecm_grade_level96",
      "group": "",
      "id": "dds32878392117",
      "serial_num": "96",
      "created_by": "35991362173",
      "modification_date": "1685695822",
      "creation_date": "1685695822",
      "modified_by": "35991362173",
      "text": "Comment",
      "field_key": "ecm_grade_level96",
      "table": "ecm_grade_level",
      "field_identifier": "comment"
    }
  },
  "form_order": [
    "id",
    "ecm_grade_level94",
    "ecm_grade_level106",
    "ecm_grade_level95",
    "ecm_grade_level96",
    "serial_num",
    "creator_role",
    "created_by",
    "creation_date",
    "modified_by",
    "modification_date",
    "ip_address",
    "device_id",
    "record_status"
  ]
}